cell_data_loader/__init__.py
cell_data_loader/base_dataset.py
cell_data_loader/cell_data_loader.py
cell_data_loader/util.py
cell_data_loader-0.0.39.dist-info/METADATA
cell_data_loader-0.0.39.dist-info/WHEEL
cell_data_loader-0.0.39.dist-info/RECORD
