Metadata-Version: 2.4
Name: cell_data_loader
Version: 0.0.39
Summary: Converts general images of cells into formats and labels for deep learning pipelines
Project-URL: Homepage, https://github.com/mleming/CellDataLoader
Author-email: Matt Leming <mleming@mgh.harvard.edu>
Maintainer-email: Matt Leming <mleming@mgh.harvard.edu>
License: MIT License
Keywords: biomedical,cell,cell image,cellpose,csz,dataloader
Requires-Python: >=3.8
Requires-Dist: cellpose==3.1.0
Requires-Dist: numpy==1.22.0
Requires-Dist: opencv-python>=4.5.4
Requires-Dist: pillow
Requires-Dist: scikit-image
Requires-Dist: scipy
Requires-Dist: slideio==2.4.1
Requires-Dist: torch>=2.0.0
Requires-Dist: torchvision
